newtabmagic.py
newtabmagic-0.1.0.dist-info/DESCRIPTION.rst
newtabmagic-0.1.0.dist-info/METADATA
newtabmagic-0.1.0.dist-info/metadata.json
newtabmagic-0.1.0.dist-info/RECORD
newtabmagic-0.1.0.dist-info/top_level.txt
newtabmagic-0.1.0.dist-info/WHEEL
