Metadata-Version: 2.0
Name: newtabmagic
Version: 0.1.0
Summary: IPython CLI for viewing documentation in the browser
Home-page: https://github.com/etgalloway/newtabmagic
Author: Eric Galloway
Author-email: ericgalloway@gmail.com
License: UNKNOWN
Keywords: CLI documentation IPython pydoc
Platform: UNKNOWN
Classifier: Framework :: IPython
Classifier: License :: OSI Approved :: BSD License
Classifier: Operating System :: OS Independent
Classifier: Programming Language :: Python
Classifier: Programming Language :: Python :: 2
Classifier: Programming Language :: Python :: 3
Classifier: Programming Language :: Python :: 2.7
Classifier: Programming Language :: Python :: 3.3
Classifier: Programming Language :: Python :: 3.4
Requires-Dist: ipython
